mrivis/__init__.py
mrivis/_version.py
mrivis/base.py
mrivis/color_maps.py
mrivis/config.py
mrivis/utils.py
mrivis/workflow.py
mrivis-0.4.dist-info/METADATA
mrivis-0.4.dist-info/WHEEL
mrivis-0.4.dist-info/licenses/AUTHORS.rst
mrivis-0.4.dist-info/licenses/LICENSE
mrivis-0.4.dist-info/RECORD
