Metadata-Version: 2.4
Name: mrivis
Version: 0.4
Summary: Intuitive high-level classes for visualization of medical imaging data
Project-URL: Homepage, https://github.com/raamana/mrivis
Author-email: Pradeep Reddy Raamana <raamana@gmail.com>
License-Expression: Apache-2.0
License-File: AUTHORS.rst
License-File: LICENSE
Keywords: mrivis
Classifier: Development Status :: 2 - Pre-Alpha
Classifier: Intended Audience :: Developers
Classifier: License :: OSI Approved :: MIT License
Classifier: Natural Language :: English
Classifier: Programming Language :: Python :: 3.13
Requires-Dist: matplotlib
Requires-Dist: nibabel
Requires-Dist: numpy
Requires-Dist: scipy
